atlas_aws_autodownload/__init__.py
atlas_aws_autodownload/cli.py
atlas_aws_autodownload/core.py
atlas_aws_autodownload-1.0.3.dist-info/licenses/LICENSE
atlas_aws_autodownload-1.0.3.dist-info/METADATA
atlas_aws_autodownload-1.0.3.dist-info/WHEEL
atlas_aws_autodownload-1.0.3.dist-info/entry_points.txt
atlas_aws_autodownload-1.0.3.dist-info/top_level.txt
atlas_aws_autodownload-1.0.3.dist-info/RECORD
