Metadata-Version: 2.4
Name: atlas-aws-autodownload
Version: 1.0.3
Summary: A Python tool for downloading files from AWS S3 bucket with configuration file support
Home-page: https://github.com/yourusername/atlas-aws-autodownload
Author: Your Name
Author-email: Haopeng Yu <hyu@atlasbioinfo.com>
Maintainer-email: Haopeng Yu <hyu@atlasbioinfo.com>
License: MIT
Project-URL: Homepage, https://github.com/atlasbioinfo/atlas_bgi_aws_autodownload
Project-URL: Documentation, https://github.com/atlasbioinfo/atlas_bgi_aws_autodownload/blob/main/README.md
Project-URL: Repository, https://github.com/atlasbioinfo/atlas_bgi_aws_autodownload
Project-URL: Bug Tracker, https://github.com/atlasbioinfo/atlas-aws-autodownload/issues
Keywords: aws,s3,download,boto3,atlas
Classifier: Development Status :: 4 - Beta
Classifier: Intended Audience :: Developers
Classifier: License :: OSI Approved :: MIT License
Classifier: Operating System :: OS Independent
Classifier: Programming Language :: Python :: 3
Classifier: Programming Language :: Python :: 3.7
Classifier: Programming Language :: Python :: 3.8
Classifier: Programming Language :: Python :: 3.9
Classifier: Programming Language :: Python :: 3.10
Classifier: Programming Language :: Python :: 3.11
Classifier: Programming Language :: Python :: 3.12
Classifier: Topic :: Internet :: WWW/HTTP
Classifier: Topic :: Software Development :: Libraries :: Python Modules
Classifier: Topic :: System :: Archiving :: Backup
Requires-Python: >=3.7
License-File: LICENSE
Requires-Dist: boto3>=1.26.0
Requires-Dist: tqdm>=4.64.0
Dynamic: author
Dynamic: home-page
Dynamic: license-file
Dynamic: requires-python
